{
    "type": "minecraft:crafting_shaped",
    "group": "bibliocraft",
    "pattern": [
        "ISI",
        "IFI",
        "ISI"
    ],
    "key": {
        "S": {
            "item": "minecraft:wooden_slab",
            "data": 2
        },
        "I": {
            "item": "minecraft:stick"
        },
        "F": {
            "item": "bibliocraft:paintingframeborderless",
            "data": 2
        }
    },
    "result": {
        "item": "bibliocraft:paintingframemiddle",
        "data": 2
    }
}
