{
    "type": "minecraft:crafting_shapeless",
    "group": "bibliocraft",
    "ingredients": [
        {
            "item": "minecraft:dye",
            "data": 5
        },
      [
        {
        "item": "bibliocraft:lanterngold",
        "data": 0
        },
        {
        "item": "bibliocraft:lanterngold",
        "data": 1
        },
        {
        "item": "bibliocraft:lanterngold",
        "data": 2
        },
        {
        "item": "bibliocraft:lanterngold",
        "data": 3
        },
        {
        "item": "bibliocraft:lanterngold",
        "data": 4
        },
        {
        "item": "bibliocraft:lanterngold",
        "data": 5
        },
        {
        "item": "bibliocraft:lanterngold",
        "data": 6
        },
        {
        "item": "bibliocraft:lanterngold",
        "data": 7
        },
        {
        "item": "bibliocraft:lanterngold",
        "data": 8
        },
        {
        "item": "bibliocraft:lanterngold",
        "data": 9
        },
        {
        "item": "bibliocraft:lanterngold",
        "data": 10
        },
        {
        "item": "bibliocraft:lanterngold",
        "data": 11
        },
        {
        "item": "bibliocraft:lanterngold",
        "data": 12
        },
        {
        "item": "bibliocraft:lanterngold",
        "data": 14
        },
        {
        "item": "bibliocraft:lanterngold",
        "data": 15
        }
      ]
    ],
    "result": {
        "item": "bibliocraft:lanterngold",
        "data": 12
    }
}
